LICENSE
MANIFEST.in
README.rst
setup.py
awscommons/__init__.py
awscommons/iam_management.py
awscommons/lambda_management.py
awscommons.egg-info/PKG-INFO
awscommons.egg-info/SOURCES.txt
awscommons.egg-info/dependency_links.txt
awscommons.egg-info/requires.txt
awscommons.egg-info/top_level.txt
test/test_iam_management.py
test/test_lambda_management.py