Metadata-Version: 1.1
Name: awscommons
Version: 1.0.0a4
Summary: Helpful utilities for managing AWS
Home-page: https://github.com/jcmturner/aws-python-commons
Author: Jonathan Turner
Author-email: jt@jtnet.co.uk
License: Apache Software License
Keywords: aws cloud development
Platform: UNKNOWN
Classifier: Development Status :: 3 - Alpha
Classifier: Intended Audience :: Developers
Classifier: Topic :: Software Development :: Libraries :: Python Modules
Classifier: License :: OSI Approved :: Apache Software License
Classifier: Programming Language :: Python :: 2.7
